dln_api/__init__.py
dln_api/api.py
dln_api/constants.py
dln_api/errors.py
dln_api/types.py
dln_api/libs/__init__.py
dln_api/libs/x64.a
dln_api/libs/x64.dll
dln_api/libs/x64.so
dln_api/libs/x86.a
dln_api/libs/x86.dll
dln_api/spi_master/__init__.py
dln_api/spi_master/api.py
dln_api/spi_slave/__init__.py
dln_api/spi_slave/api.py
dln_api-0.1.4.dist-info/METADATA
dln_api-0.1.4.dist-info/WHEEL
dln_api-0.1.4.dist-info/entry_points.txt
dln_api-0.1.4.dist-info/top_level.txt
dln_api-0.1.4.dist-info/RECORD
