Metadata-Version: 2.1
Name: dln-api
Version: 0.1.4
Summary: DLN API package
Author-email: Guillaume Sottas <guillaumesottas@gmail.com>
License: BSD License
Project-URL: Repository, https://github.com/Sauci/dln-api
Classifier: Programming Language :: Python :: 3
Classifier: License :: OSI Approved :: BSD License
Classifier: Operating System :: Microsoft :: Windows
Classifier: Operating System :: Unix
Requires-Python: >=3.10
